{"values":{"bun":"2","node":"40","deno":"35","graaljs":"12","hermes":"8","llrt":"8","txiki.js":"8","quickjs":"7","quickjs-ng":"8","mujs":"","mujs-pgo":"","mujs-one":"","xst":"40028","JavaScriptCore":"2","v8":"33","spidermonkey":"1","JerryScript":"","primjs":"10","rquickjs":"9","rquickjs-pgo":"8","ChakraCore":"42","duktape":"","nova":"2199","boa":"","engine262":"3554","ladybird":"\u001b[35;1m12\u001b[0m","goja":"","kiesel":"28","mozjs":"1","jint":"34","dune":"\u001b[33m40\u001b[0m","jjs":"","njs":"5","ringo":"47","lo":"36","spiderfire":"2","bare":"45","hako":"","quickjs-emscripten":"14"},"reassign":{"bun":"15","node":"23","deno":"20","graaljs":"95","hermes":"12","llrt":"21","txiki.js":"17","quickjs":"17","quickjs-ng":"23","mujs":"28","mujs-pgo":"19","mujs-one":"31","xst":"40714","JavaScriptCore":"14","v8":"19","spidermonkey":"5","JerryScript":"","primjs":"21","rquickjs":"23","rquickjs-pgo":"20","ChakraCore":"39","duktape":"25","nova":"2641","boa":"","engine262":"19172","ladybird":"\u001b[35;1m65\u001b[0m","goja":"","kiesel":"123","mozjs":"6","jint":"170","dune":"\u001b[33m21\u001b[0m","jjs":"208","njs":"15","ringo":"107","lo":"19","spiderfire":"5","bare":"20","hako":"","quickjs-emscripten":"31"}}
