{"reassign":{"bun":"14","node":"24","deno":"21","graaljs":"95","hermes":"24","llrt":"36","txiki.js":"23","quickjs":"27","quickjs-ng":"20","mujs":"29","mujs-pgo":"31","xst":"","JavaScriptCore":"13","v8":"16","spidermonkey":"6","rquickjs":"33","rquickjs-pgo":"36","ChakraCore":"36","duktape":"65","boa":"72","engine262":"22330","goja":"","kiesel":"144","jint":"245","dune":"\u001b[33m21\u001b[0m","spiderfire":"6","quickjs-emscripten":"41"},"values":{"bun":"2","node":"41","deno":"37","graaljs":"14","hermes":"12","llrt":"18","txiki.js":"9","quickjs":"10","quickjs-ng":"8","mujs":"","mujs-pgo":"","xst":"","JavaScriptCore":"1","v8":"28","spidermonkey":"1","rquickjs":"16","rquickjs-pgo":"16","ChakraCore":"40","duktape":"","boa":"21","engine262":"3993","goja":"","kiesel":"19","jint":"58","dune":"\u001b[33m41\u001b[0m","spiderfire":"1","quickjs-emscripten":"17"}}
